c_matmul.cpython-313-darwin.so
c_matmul.py
mx/__init__.py
mx/linear.py
mx/module.py
mx/mtrx.py
mx/tensor.py
qmx-0.1.0.dist-info/METADATA
qmx-0.1.0.dist-info/WHEEL
qmx-0.1.0.dist-info/top_level.txt
qmx-0.1.0.dist-info/RECORD
