Metadata-Version: 2.4
Name: qmx
Version: 0.1.0
Summary: Pure C accelerated matrix operations for LLMs
Home-page: https://github.com/micwill755/mtrx
Author: TBD
Author-email: Michael Williams <mww565@icloud.com>
Project-URL: Homepage, https://github.com/micwill755/qmx
Project-URL: Repository, https://github.com/micwill755/qmx
Requires-Python: >=3.7
Dynamic: author
Dynamic: home-page
Dynamic: requires-python
